heroku_env/__init__.py
heroku_env/__main__.py
heroku_env/cli.py
heroku_env/constants.py
heroku_env/exceptions.py
heroku_env/heroku_env.py
heroku_env/param_types.py
heroku.env-0.6.1.dist-info/LICENSE
heroku.env-0.6.1.dist-info/METADATA
heroku.env-0.6.1.dist-info/WHEEL
heroku.env-0.6.1.dist-info/entry_points.txt
heroku.env-0.6.1.dist-info/top_level.txt
heroku.env-0.6.1.dist-info/RECORD
