Metadata-Version: 2.1
Name: heroku.env
Version: 0.6.1
Summary: CLI tool to manipulate environment variables on Heroku with local .env files
Home-page: https://github.com/viseshrp/heroku.env
Author: Visesh Prasad
Author-email: visesh@live.com
Maintainer: Visesh Prasad
Maintainer-email: visesh@live.com
License: MIT license
Project-URL: Documentation, https://github.com/viseshrp/heroku.env
Project-URL: Changelog, https://github.com/viseshrp/heroku.env/blob/main/CHANGELOG.rst
Project-URL: Bug Tracker, https://github.com/viseshrp/heroku.env/issues
Project-URL: Source Code, https://github.com/viseshrp/heroku.env
Keywords: heroku.env heroku env herokuenv heroku_env environment variables load
Classifier: Development Status :: 4 - Beta
Classifier: Environment :: Console
Classifier: Intended Audience :: Developers
Classifier: License :: OSI Approved :: MIT License
Classifier: Operating System :: OS Independent
Classifier: Natural Language :: English
Classifier: Programming Language :: Python :: 3.7
Classifier: Programming Language :: Python :: 3.8
Classifier: Programming Language :: Python :: 3.9
Classifier: Programming Language :: Python :: 3.10
Classifier: Topic :: Software Development :: Libraries :: Python Modules
Requires-Python: >=3.7
License-File: LICENSE
Requires-Dist: Click (>=8.1.1)
Requires-Dist: heroku3 (>=5.1.4)
Requires-Dist: colorama (>=0.4.4)
